traceprintplus/__init__.py
traceprintplus/core.py
traceprintplus-0.4.dist-info/METADATA
traceprintplus-0.4.dist-info/WHEEL
traceprintplus-0.4.dist-info/top_level.txt
traceprintplus-0.4.dist-info/RECORD
