Metadata-Version: 2.4
Name: traceprintplus
Version: 0.4
Dynamic: description
Dynamic: description-content-type
